{
  "global_image_tag": "ホラー",
  "scenes": [
    {
      "scene_id": "scene_01",
      "start_sec": 0.0,
      "duration": 2.73,
      "text": "“メンタルが強い人”\n感情を殺してるだけ？",
      "type": "main_title",
      "tags": [],
      "parent_scene_id": "001",
      "emotion": "emotion: 悲しみ (sadness)"
    },
    {
      "scene_id": "scene_02",
      "start_sec": 2.73,
      "duration": 4.12,
      "text": "“メンタルが強い”は\n“感情を感じにくい”\nとは別物",
      "type": "title",
      "tags": [],
      "parent_scene_id": "002",
      "emotion": "emotion: 落ち着き (calm)"
    },
    {
      "scene_id": "scene_03",
      "start_sec": 6.85,
      "duration": 1.81,
      "text": "本当にレジリエンスが高い人は、",
      "type": "summary",
      "tags": [],
      "parent_scene_id": "002",
      "emotion": "emotion: 落ち着き (calm)"
    },
    {
      "scene_id": "scene_04",
      "start_sec": 8.66,
      "duration": 1.51,
      "text": "感情を抑えるのではなく、",
      "type": "summary",
      "tags": [],
      "parent_scene_id": "002",
      "emotion": "emotion: 落ち着き (calm)"
    },
    {
      "scene_id": "scene_05",
      "start_sec": 10.18,
      "duration": 1.88,
      "text": "適切に感じて、処理している。",
      "type": "summary",
      "tags": [],
      "parent_scene_id": "003",
      "emotion": "emotion: 悲しみ (sadness)"
    },
    {
      "scene_id": "scene_06",
      "start_sec": 12.05,
      "duration": 1.76,
      "text": "感情を押し殺すだけの対応は、",
      "type": "summary",
      "tags": [],
      "parent_scene_id": "003",
      "emotion": "emotion: 悲しみ (sadness)"
    },
    {
      "scene_id": "scene_07",
      "start_sec": 13.81,
      "duration": 0.96,
      "text": "むしろトラウマや",
      "type": "summary",
      "tags": [],
      "parent_scene_id": "003",
      "emotion": "emotion: 悲しみ (sadness)"
    },
    {
      "scene_id": "scene_08",
      "start_sec": 14.77,
      "duration": 1.51,
      "text": "心理的ダメージのリスクを",
      "type": "summary",
      "tags": [],
      "parent_scene_id": "004",
      "emotion": "emotion: 恐れ (fear)"
    },
    {
      "scene_id": "scene_09",
      "start_sec": 16.29,
      "duration": 1.58,
      "text": "高めることが報告されている。",
      "type": "summary",
      "tags": [],
      "parent_scene_id": "004",
      "emotion": "emotion: 恐れ (fear)"
    },
    {
      "scene_id": "scene_10",
      "start_sec": 17.87,
      "duration": 3.62,
      "text": "感情を“感じない癖”が\n自律神経を狂わせる",
      "type": "title",
      "tags": [],
      "parent_scene_id": "005",
      "emotion": "emotion: 無感情・中立 (neutral)"
    },
    {
      "scene_id": "scene_11",
      "start_sec": 21.48,
      "duration": 1.79,
      "text": "怒りや悲しみを無視し続けると、",
      "type": "summary",
      "tags": [],
      "parent_scene_id": "005",
      "emotion": "emotion: 無感情・中立 (neutral)"
    },
    {
      "scene_id": "scene_12",
      "start_sec": 23.27,
      "duration": 1.93,
      "text": "交感神経と副交感神経の",
      "type": "summary",
      "tags": [],
      "parent_scene_id": "005",
      "emotion": "emotion: 無感情・中立 (neutral)"
    },
    {
      "scene_id": "scene_13",
      "start_sec": 25.21,
      "duration": 1.34,
      "text": "バランスが崩れやすくなる。",
      "type": "summary",
      "tags": [],
      "parent_scene_id": "006",
      "emotion": "emotion: 悲しみ (sadness)"
    },
    {
      "scene_id": "scene_14",
      "start_sec": 26.55,
      "duration": 2.81,
      "text": "その結果、睡眠障害・慢性疲労・",
      "type": "summary",
      "tags": [],
      "parent_scene_id": "006",
      "emotion": "emotion: 悲しみ (sadness)"
    },
    {
      "scene_id": "scene_15",
      "start_sec": 29.35,
      "duration": 1.28,
      "text": "集中力の低下など、",
      "type": "summary",
      "tags": [],
      "parent_scene_id": "006",
      "emotion": "emotion: 悲しみ (sadness)"
    },
    {
      "scene_id": "scene_16",
      "start_sec": 30.63,
      "duration": 2.04,
      "text": "身体症状として現れることがある。",
      "type": "summary",
      "tags": [],
      "parent_scene_id": "007",
      "emotion": "emotion: 無感情・中立 (neutral)"
    },
    {
      "scene_id": "scene_17",
      "start_sec": 32.67,
      "duration": 2.85,
      "text": "“強くあらねば”\nという信念が\n心を壊すことがある",
      "type": "title",
      "tags": [],
      "parent_scene_id": "008",
      "emotion": "emotion: 悲しみ (sadness)"
    },
    {
      "scene_id": "scene_18",
      "start_sec": 35.52,
      "duration": 0.92,
      "text": "「泣いてはいけない」",
      "type": "summary",
      "tags": [],
      "parent_scene_id": "008",
      "emotion": "emotion: 悲しみ (sadness)"
    },
    {
      "scene_id": "scene_19",
      "start_sec": 36.44,
      "duration": 1.3,
      "text": "「弱音を吐くのは甘え」",
      "type": "summary",
      "tags": [],
      "parent_scene_id": "008",
      "emotion": "emotion: 悲しみ (sadness)"
    },
    {
      "scene_id": "scene_20",
      "start_sec": 37.74,
      "duration": 1.95,
      "text": "という信念を内面化している人は、",
      "type": "summary",
      "tags": [],
      "parent_scene_id": "009",
      "emotion": "emotion: 悲しみ (sadness)"
    },
    {
      "scene_id": "scene_21",
      "start_sec": 39.69,
      "duration": 1.69,
      "text": "自己否定感が慢性化しやすい。",
      "type": "summary",
      "tags": [],
      "parent_scene_id": "009",
      "emotion": "emotion: 悲しみ (sadness)"
    },
    {
      "scene_id": "scene_22",
      "start_sec": 41.38,
      "duration": 1.0,
      "text": "このような認知は",
      "type": "summary",
      "tags": [],
      "parent_scene_id": "009",
      "emotion": "emotion: 悲しみ (sadness)"
    },
    {
      "scene_id": "scene_23",
      "start_sec": 42.38,
      "duration": 1.86,
      "text": "自己価値の低下や孤立感を強め、",
      "type": "summary",
      "tags": [],
      "parent_scene_id": "010",
      "emotion": "emotion: 悲しみ (sadness)"
    },
    {
      "scene_id": "scene_24",
      "start_sec": 44.23,
      "duration": 1.65,
      "text": "長期的に心を脆くしていく。",
      "type": "summary",
      "tags": [],
      "parent_scene_id": "010",
      "emotion": "emotion: 悲しみ (sadness)"
    }
  ]
}